{"Game":{"0":"Loadout Steam Launch Starter Pack","1":"The Princess' Heart","2":"Another Perspective","3":"Incandescent","4":"Eschalon: Book I","5":"Gratuitous Space Battles: The Parasites","6":"Kromaia","7":"OMG Zombies!","8":"Bierzerkers","9":"Chicken Invaders 4"},"Game Link":{"0":"http:\/\/store.steampowered.com\/app\/271520\/?snr=1_237_querypaginated__104_240","1":"http:\/\/store.steampowered.com\/app\/378830\/?snr=1_237_querypaginated__104_240","2":"http:\/\/store.steampowered.com\/app\/305920\/?snr=1_237_querypaginated__104_240","3":"http:\/\/store.steampowered.com\/app\/380550\/?snr=1_237_querypaginated__104_240","4":"http:\/\/store.steampowered.com\/app\/25600\/?snr=1_237_querypaginated__104_240","5":"http:\/\/store.steampowered.com\/app\/41816\/?snr=1_237_querypaginated__104_240","6":"http:\/\/store.steampowered.com\/app\/285980\/?snr=1_237_querypaginated__104_240","7":"http:\/\/store.steampowered.com\/app\/259870\/?snr=1_237_querypaginated__104_240","8":"http:\/\/store.steampowered.com\/app\/348460\/?snr=1_237_querypaginated__104_240","9":"http:\/\/store.steampowered.com\/app\/301300\/?snr=1_237_querypaginated__104_240"},"Game Tags":{"0":"\n Free to Play, Action, Indie, Third-Person Shooter\n","1":"\n Adventure, RPG, Indie, RPGMaker\n","2":"\n Indie, Adventure, Platformer, Puzzle\n","3":"\n Action, Indie\n","4":"\n RPG, Indie, Turn-Based, Isometric\n","5":"\n Indie, Simulation, Strategy\n","6":"\n Indie, Action, Shoot 'Em Up, Arcade\n","7":"\n Zombies, Action, Strategy, Indie\n","8":"\n Early Access, Action, Indie, Multiplayer\n","9":"\n Action, Indie, Casual\n"},"OSType":{"0":["win"],"1":["win"],"2":["win"],"3":["win"],"4":["win","mac","linux","steamplay"],"5":["win"],"6":["win"],"7":["win"],"8":["win"],"9":["win","mac","linux","steamplay"]},"Value":{"0":10,"1":11,"2":12,"3":13,"4":14,"5":15,"6":16,"7":17,"8":18,"9":19}}