{"Game":{"0":"UnEpic","1":"Freight Tycoon Inc.","2":"Reflections","3":"Ticket to Ride","4":"The Escapists - Alcatraz","5":"McPixel","6":"CAT Interstellar","7":"Waste Walkers Role Playing Game DLC","8":"Trials 2: Second Edition","9":"Rememoried"},"Game Link":{"0":"http:\/\/store.steampowered.com\/app\/233980\/?snr=1_237_querypaginated__104_95","1":"http:\/\/store.steampowered.com\/app\/289340\/?snr=1_237_querypaginated__104_95","2":"http:\/\/store.steampowered.com\/app\/352360\/?snr=1_237_querypaginated__104_95","3":"http:\/\/store.steampowered.com\/app\/108200\/?snr=1_237_querypaginated__104_95","4":"http:\/\/store.steampowered.com\/app\/349350\/?snr=1_237_querypaginated__104_95","5":"http:\/\/store.steampowered.com\/app\/220860\/?snr=1_237_querypaginated__104_95","6":"http:\/\/store.steampowered.com\/app\/384740\/?snr=1_237_querypaginated__104_95","7":"http:\/\/store.steampowered.com\/app\/395690\/?snr=1_237_querypaginated__104_95","8":"http:\/\/store.steampowered.com\/app\/16600\/?snr=1_237_querypaginated__104_95","9":"http:\/\/store.steampowered.com\/app\/368450\/?snr=1_237_querypaginated__104_95"},"Game Tags":{"0":"\n RPG, Indie, Platformer, Metroidvania\n","1":"\n Strategy, Management, Simulation, Economy\n","2":"\n Early Access, Adventure, Indie, First-Person\n","3":"\n Board Game, Strategy, Casual, Multiplayer\n","4":"\n Simulation, Action, Adventure, Indie\n","5":"\n Indie, Point & Click, Comedy, Puzzle\n","6":"\n Early Access, Adventure, Indie, Exploration\n","7":"\n Strategy, Action, Adventure, RPG\n","8":"\n Racing, Indie, Sports\n","9":"\n Indie, Adventure, Surreal, First-Person\n"},"OSType":{"0":["win","mac","linux","steamplay"],"1":["win"],"2":["win","mac","linux","steamplay"],"3":["win","mac","linux","steamplay"],"4":["win"],"5":["win","mac","steamplay"],"6":["win"],"7":["win"],"8":["win"],"9":["win","mac","steamplay"]},"Value":{"0":10,"1":11,"2":12,"3":13,"4":14,"5":15,"6":16,"7":17,"8":18,"9":19}}