{"Game":{"0":"Goat Simulator: Original Soundtrack","1":"Foosball - Street Edition","2":"Fantasy Grounds - D&D Warlock Class Pack","3":"Space Station Alpha","4":"DRAGON: A Game About a Dragon","5":"The Dream Machine: Chapter 5","6":"Evoland 2 - Soundtrack","7":"Vox Populi Vox Dei 2","8":"Never Alone: Original Soundtrack","9":"Prismatica"},"Game Link":{"0":"http:\/\/store.steampowered.com\/app\/335350\/?snr=1_237_querypaginated__104_243","1":"http:\/\/store.steampowered.com\/app\/280830\/?snr=1_237_querypaginated__104_243","2":"http:\/\/store.steampowered.com\/app\/360112\/?snr=1_237_querypaginated__104_243","3":"http:\/\/store.steampowered.com\/app\/341930\/?snr=1_237_querypaginated__104_243","4":"http:\/\/store.steampowered.com\/app\/351150\/?snr=1_237_querypaginated__104_243","5":"http:\/\/store.steampowered.com\/app\/330260\/?snr=1_237_querypaginated__104_243","6":"http:\/\/store.steampowered.com\/app\/396460\/?snr=1_237_querypaginated__104_243","7":"http:\/\/store.steampowered.com\/app\/345120\/?snr=1_237_querypaginated__104_243","8":"http:\/\/store.steampowered.com\/app\/351740\/?snr=1_237_querypaginated__104_243","9":"http:\/\/store.steampowered.com\/app\/377500\/?snr=1_237_querypaginated__104_243"},"Game Tags":{"0":"\n Simulation, Indie, Casual, Funny\n","1":"\n Sports, Indie, Casual, Football\n","2":"\n Indie, RPG, Strategy, Turn-Based\n","3":"\n Simulation, Strategy, Indie, Space\n","4":"\n Indie, Adventure, Casual, RPG\n","5":"\n Casual, Indie, Adventure, Atmospheric\n","6":"\n Action, Adventure, RPG, Indie\n","7":"\n Indie, Action, Adventure, Pixel Graphics\n","8":"\n Action, Adventure, Indie\n","9":"\n Indie, Casual, Strategy, Puzzle\n"},"OSType":{"0":["win","mac","linux","steamplay"],"1":["win","mac","linux","steamplay"],"2":["win"],"3":["win","mac","linux","steamplay"],"4":["win"],"5":["win","mac","steamplay"],"6":["win"],"7":["win"],"8":["win","mac","steamplay"],"9":["win","mac","steamplay"]},"Value":{"0":10,"1":11,"2":12,"3":13,"4":14,"5":15,"6":16,"7":17,"8":18,"9":19}}