{"Game":{"0":"Sym","1":"WonderCat Adventures","2":"A Druid's Duel","3":"Awesomenauts - Demon Sk\u00f8lldir Skin","4":"Khaba","5":"YOU DON'T KNOW JACK Vol. 2","6":"Escape Goat 2","7":"Tkl Online","8":"Gundemonium Recollection","9":"Eador: Genesis"},"Game Link":{"0":"http:\/\/store.steampowered.com\/app\/342100\/?snr=1_237_querypaginated__104_229","1":"http:\/\/store.steampowered.com\/app\/384120\/?snr=1_237_querypaginated__104_229","2":"http:\/\/store.steampowered.com\/app\/333970\/?snr=1_237_querypaginated__104_229","3":"http:\/\/store.steampowered.com\/app\/230885\/?snr=1_237_querypaginated__104_229","4":"http:\/\/store.steampowered.com\/app\/338110\/?snr=1_237_querypaginated__104_229","5":"http:\/\/store.steampowered.com\/app\/259940\/?snr=1_237_querypaginated__104_229","6":"http:\/\/store.steampowered.com\/app\/255340\/?snr=1_237_querypaginated__104_229","7":"http:\/\/store.steampowered.com\/app\/335770\/?snr=1_237_querypaginated__104_229","8":"http:\/\/store.steampowered.com\/app\/92200\/?snr=1_237_querypaginated__104_229","9":"http:\/\/store.steampowered.com\/app\/235660\/?snr=1_237_querypaginated__104_229"},"Game Tags":{"0":"\n Indie, Puzzle-Platformer, Platformer\n","1":"\n Action, Indie, Casual, Platformer\n","2":"\n Indie, Strategy, Multiplayer, Turn-Based Strategy\n","3":"\n Action, Indie, Strategy\n","4":"\n Casual, Adventure, Puzzle, Indie\n","5":"\n Casual, Indie, Comedy\n","6":"\n Indie, Platformer, Puzzle, Casual\n","7":"\n Action, Indie, RPG, Action RPG\n","8":"\n Bullet Hell, Shoot 'Em Up, Anime, Indie\n","9":"\n Strategy, Indie, Turn-Based Strategy, RPG\n"},"OSType":{"0":["win","mac","steamplay"],"1":["win"],"2":["win","mac","linux","steamplay"],"3":["win","mac","linux","steamplay"],"4":["win","mac","steamplay"],"5":["win"],"6":["win","mac","linux","steamplay"],"7":["win"],"8":["win"],"9":["win"]},"Value":{"0":10,"1":11,"2":12,"3":13,"4":14,"5":15,"6":16,"7":17,"8":18,"9":19}}