{"Game":{"0":"Talisman - Character Pack #8 - Apprentice Mage","1":"Talisman - Character Pack #6 - Gambler","2":"Snakebird","3":"Kyn","4":"Vector","5":"NeonXSZ","6":"Fantasy Grounds - D&D Scourge of the Sword Coast","7":"Sword of the Stars: The Pit - The Pilgrim DLC","8":"Drifter","9":"Euro Truck Simulator 2 - Czech Paint Jobs Pack"},"Game Link":{"0":"http:\/\/store.steampowered.com\/app\/267774\/?snr=1_237_querypaginated__104_163","1":"http:\/\/store.steampowered.com\/app\/267771\/?snr=1_237_querypaginated__104_163","2":"http:\/\/store.steampowered.com\/app\/357300\/?snr=1_237_querypaginated__104_163","3":"http:\/\/store.steampowered.com\/app\/314560\/?snr=1_237_querypaginated__104_163","4":"http:\/\/store.steampowered.com\/app\/248970\/?snr=1_237_querypaginated__104_163","5":"http:\/\/store.steampowered.com\/app\/296010\/?snr=1_237_querypaginated__104_163","6":"http:\/\/store.steampowered.com\/app\/390750\/?snr=1_237_querypaginated__104_163","7":"http:\/\/store.steampowered.com\/app\/291790\/?snr=1_237_querypaginated__104_163","8":"http:\/\/store.steampowered.com\/app\/259450\/?snr=1_237_querypaginated__104_163","9":"http:\/\/store.steampowered.com\/app\/318511\/?snr=1_237_querypaginated__104_163"},"Game Tags":{"0":"\n Strategy, RPG, Indie\n","1":"\n Strategy, RPG, Indie\n","2":"\n Indie, Puzzle, Difficult, Cute\n","3":"\n Action, RPG, Indie, Adventure\n","4":"\n Parkour, Indie, Action, Platformer\n","5":"\n Early Access, Action, Indie, RPG\n","6":"\n RPG, Indie, Strategy, Utilities\n","7":"\n Indie, RPG, Strategy, Casual\n","8":"\n Early Access, Simulation, Indie, Space\n","9":"\n Simulation, Indie\n"},"OSType":{"0":["win","mac","steamplay"],"1":["win","mac","steamplay"],"2":["win","mac","linux","steamplay"],"3":["win"],"4":["win"],"5":["win","mac","linux","steamplay"],"6":["win"],"7":["win","mac","linux","steamplay"],"8":["win","mac","linux","steamplay"],"9":["win","mac","linux","steamplay"]},"Value":{"0":10,"1":11,"2":12,"3":13,"4":14,"5":15,"6":16,"7":17,"8":18,"9":19}}